easydsi/__init__.py
easydsi/heap/__init__.py
easydsi/heap/heap.py
easydsi/heap/heap_utils.py
easydsi/linked_list/__init__.py
easydsi/queue/__init__.py
easydsi/queue/queue.py
easydsi/queue/queue_utils.py
easydsi/stack/__init__.py
easydsi/stack/stack.py
easydsi/stack/stack_exceptions.py
easydsi/stack/stack_utils.py
easydsi/tree/__init__.py
easydsi/tree/binary_tree.py
easydsi/tree/tree.py
easydsi/tree/tree_utils.py
easydsi-2.0.1.dist-info/licenses/LICENSE.txt
easydsi-2.0.1.dist-info/METADATA
easydsi-2.0.1.dist-info/WHEEL
easydsi-2.0.1.dist-info/top_level.txt
easydsi-2.0.1.dist-info/RECORD
