Metadata-Version: 2.4
Name: easydsi
Version: 2.0.1
Summary: A Python library that helps developers implement data structures & algorithms easily.
Home-page: https://github.com/fazil2003/easydsi
Author: Mohamed Fazil
Author-email: Mohamed Fazil <mohamedfazil463@gmail.com>
License: MIT
Project-URL: Homepage, https://github.com/fazil2003/easydsi
Project-URL: Documentation, https://github.com/fazil2003/easydsi/wiki
Project-URL: Source, https://github.com/fazil2003/easydsi
Project-URL: Issues, https://github.com/fazil2003/easydsi/issues
Requires-Python: >=3.6
License-File: LICENSE.txt
Requires-Dist: multipledispatch==0.6.0
Requires-Dist: binarytree==6.5.1
Dynamic: author
Dynamic: home-page
Dynamic: license-file
Dynamic: requires-python
